multimodal_parser/__init__.py
multimodal_parser/markdown.py
multimodal_parser/img_analysis.prompt
multimodal_parser/md_prompt.j2
multimodal_parser-0.1.1.dist-info/METADATA
multimodal_parser-0.1.1.dist-info/WHEEL
multimodal_parser-0.1.1.dist-info/licenses/LICENSE
multimodal_parser-0.1.1.dist-info/RECORD
