Metadata-Version: 2.4
Name: multimodal-parser
Version: 0.1.1
Summary: [DEPRECATED] Extract content from PDF documents using multimodal LLMs in markdown format
Project-URL: Homepage, https://github.com/iamarunbrahma/multimodal-parser
Project-URL: Repository, https://github.com/iamarunbrahma/multimodal-parser.git
Author-email: Arun Brahma <mithubrahma@gmail.com>
License-Expression: MIT
License-File: LICENSE
Classifier: Development Status :: 7 - Inactive
Classifier: Intended Audience :: Developers
Classifier: License :: OSI Approved :: MIT License
Classifier: Programming Language :: Python :: 3
Classifier: Programming Language :: Python :: 3.13
Requires-Python: >=3.13
Requires-Dist: jinja2>=3.1.4
Requires-Dist: ollama>=0.4.4
Requires-Dist: pydantic>=2.10.3
Requires-Dist: pymupdf>=1.25.1
Requires-Dist: tqdm>=4.67.1
Provides-Extra: dev
Requires-Dist: black>=24.10.0; extra == 'dev'
Requires-Dist: pytest>=8.3.4; extra == 'dev'
Requires-Dist: ruff>=0.8.3; extra == 'dev'
